admin_numeric_filter/__init__.py
admin_numeric_filter/admin.py
admin_numeric_filter/forms.py
admin_numeric_filter/static/css/admin-numeric-filter.css
admin_numeric_filter/static/js/admin-numeric-filter.js
admin_numeric_filter/static/js/nouislider.min.css
admin_numeric_filter/static/js/nouislider.min.js
admin_numeric_filter/static/js/wNumb.min.js
admin_numeric_filter/templates/admin/filter_numeric_range.html
admin_numeric_filter/templates/admin/filter_numeric_single.html
admin_numeric_filter/templates/admin/filter_numeric_slider.html
django_admin_numeric_filter-0.1.8.dist-info/LICENSE
django_admin_numeric_filter-0.1.8.dist-info/WHEEL
django_admin_numeric_filter-0.1.8.dist-info/METADATA
django_admin_numeric_filter-0.1.8.dist-info/RECORD
