Metadata-Version: 2.1
Name: django-admin-numeric-filter
Version: 0.1.8
Summary: Numeric filters for Django admin
Home-page: https://github.com/lukasvinclav/django-admin-numeric-filter
License: MIT
Keywords: django,admin,numeric,filter
Requires-Python: >=3.6
Classifier: Environment :: Web Environment
Classifier: Framework :: Django
Classifier: Intended Audience :: Developers
Classifier: License :: OSI Approved :: MIT License
Classifier: Operating System :: OS Independent
Classifier: Programming Language :: Python
Classifier: Programming Language :: Python :: 3
Classifier: Programming Language :: Python :: 3.6
Classifier: Programming Language :: Python :: 3.7
Classifier: Programming Language :: Python :: 3.8
Classifier: Programming Language :: Python :: 3.9
Classifier: Programming Language :: Python :: 3.10
Classifier: Programming Language :: Python :: 3.11
Classifier: Programming Language :: Python :: 3.10
Classifier: Programming Language :: Python :: 3.6
Classifier: Programming Language :: Python :: 3.7
Classifier: Programming Language :: Python :: 3.8
Classifier: Programming Language :: Python :: 3.9
Requires-Dist: django (>=3.2)
Project-URL: Repository, https://github.com/lukasvinclav/django-admin-numeric-filter
